{"9133adfdaf3097681555b24d3bedc500:74d58197dfb78b6db7a8776c387075ac":{"statistic":{"failed":0,"broken":0,"skipped":0,"passed":1,"unknown":0,"total":1},"items":[{"uid":"75148468bf35abb5","reportUrl":"https://assurdly.github.io/dfslab-automation-tests/21/11//#testresult/75148468bf35abb5","status":"passed","time":{"start":1745784791811,"stop":1745784792059,"duration":248}}]},"d1671f0e048572d577ead47fbbbbb6f4:e033ae124b2426054c44ca12061af730":{"statistic":{"failed":1,"broken":0,"skipped":0,"passed":0,"unknown":0,"total":1},"items":[{"uid":"d7094a168d07055b","reportUrl":"https://assurdly.github.io/dfslab-automation-tests/21/11//#testresult/d7094a168d07055b","status":"failed","statusDetails":"Status code is 400","time":{"start":1745784787052,"stop":1745784787541,"duration":489}}]},"afc121077ed9f8362d2ba913efc943cb:b93311c18124bb9fe0a781fd3df1cfd0":{"statistic":{"failed":0,"broken":0,"skipped":0,"passed":1,"unknown":0,"total":1},"items":[{"uid":"72daa42667324cb8","reportUrl":"https://assurdly.github.io/dfslab-automation-tests/21/11//#testresult/72daa42667324cb8","status":"passed","time":{"start":1745784789556,"stop":1745784790046,"duration":490}}]},"de02cb1b1a07c70b80ba0998e587a306:fea95182485bf1afe45f6880c0b53d43":{"statistic":{"failed":0,"broken":0,"skipped":0,"passed":1,"unknown":0,"total":1},"items":[{"uid":"3daada3f3de1f1f6","reportUrl":"https://assurdly.github.io/dfslab-automation-tests/21/11//#testresult/3daada3f3de1f1f6","status":"passed","time":{"start":1745784785015,"stop":1745784785204,"duration":189}}]},"ad0ccfb707208675845b349c4f2d4a19:1e01c3be57e55a3cd8765392f08240c1":{"statistic":{"failed":0,"broken":0,"skipped":0,"passed":1,"unknown":0,"total":1},"items":[{"uid":"3ee2288527a97388","reportUrl":"https://assurdly.github.io/dfslab-automation-tests/21/11//#testresult/3ee2288527a97388","status":"passed","time":{"start":1745784783760,"stop":1745784784484,"duration":724}}]},"f109f57979df6f73c20d7b631c396add:3258e2abfebd29d48e5c03cf74f53633":{"statistic":{"failed":0,"broken":0,"skipped":0,"passed":1,"unknown":0,"total":1},"items":[{"uid":"1068e1f76826da4f","reportUrl":"https://assurdly.github.io/dfslab-automation-tests/21/11//#testresult/1068e1f76826da4f","status":"passed","time":{"start":1745784796062,"stop":1745784796285,"duration":223}}]},"226e9ad94a94b944ed88d4507e12d1b0:c81c24e5d01e7831182f57334d4d581b":{"statistic":{"failed":1,"broken":0,"skipped":0,"passed":0,"unknown":0,"total":1},"items":[{"uid":"ff9facdab2f3e9d6","reportUrl":"https://assurdly.github.io/dfslab-automation-tests/21/11//#testresult/ff9facdab2f3e9d6","status":"failed","statusDetails":"Status code is 400, Message should fail if data was not fetched","time":{"start":1745784790816,"stop":1745784791085,"duration":269}}]},"a38b983fb0d15d76ad145f45d8da48ae:2f66a83e9f48389019be4e5e4a57ecc8":{"statistic":{"failed":0,"broken":1,"skipped":0,"passed":0,"unknown":0,"total":1},"items":[{"uid":"2b0767d27df405ec","reportUrl":"https://assurdly.github.io/dfslab-automation-tests/21/11//#testresult/2b0767d27df405ec","status":"broken","statusDetails":"getaddrinfo ENOTFOUND demo.dfqt.orghttps","time":{"start":1745784791088,"stop":1745784791298,"duration":210}}]},"6d4cdc3d65c86878e9e4e8050e27b356:0fd817c58e9483cee11065ea47c49fe3":{"statistic":{"failed":0,"broken":0,"skipped":0,"passed":1,"unknown":0,"total":1},"items":[{"uid":"b20b08bac03fd423","reportUrl":"https://assurdly.github.io/dfslab-automation-tests/21/11//#testresult/b20b08bac03fd423","status":"passed","time":{"start":1745784785608,"stop":1745784785850,"duration":242}}]},"dfe5f92e6b45b2e4111b1133f728906e:7a85cea52572c67f1f242960341ebcc6":{"statistic":{"failed":1,"broken":0,"skipped":0,"passed":0,"unknown":0,"total":1},"items":[{"uid":"9ed4a5438cdc37e2","reportUrl":"https://assurdly.github.io/dfslab-automation-tests/21/11//#testresult/9ed4a5438cdc37e2","status":"failed","statusDetails":"Status code is 400","time":{"start":1745784789299,"stop":1745784789554,"duration":255}}]},"b4b7a9bf415bab57069f782b28acecbc:40213bf39c5c8336a4165563d62cc523":{"statistic":{"failed":1,"broken":0,"skipped":0,"passed":0,"unknown":0,"total":1},"items":[{"uid":"cbf851f5cfeb51db","reportUrl":"https://assurdly.github.io/dfslab-automation-tests/21/11//#testresult/cbf851f5cfeb51db","status":"failed","statusDetails":"Status code is 400","time":{"start":1745784786322,"stop":1745784786554,"duration":232}}]},"ffc91b73521106a7e1c136ab2d6c12c1:0b625e035b2b10efb367621919dbf9bd":{"statistic":{"failed":0,"broken":0,"skipped":0,"passed":1,"unknown":0,"total":1},"items":[{"uid":"347379d2b87e33e8","reportUrl":"https://assurdly.github.io/dfslab-automation-tests/21/11//#testresult/347379d2b87e33e8","status":"passed","time":{"start":1745784796598,"stop":1745784796824,"duration":226}}]},"07b012a9be78363bacddbf980d518600:74d8190092d3dfa7f03ccd01e5e5d7ba":{"statistic":{"failed":0,"broken":0,"skipped":0,"passed":1,"unknown":0,"total":1},"items":[{"uid":"9d11747c10c62d32","reportUrl":"https://assurdly.github.io/dfslab-automation-tests/21/11//#testresult/9d11747c10c62d32","status":"passed","time":{"start":1745784794984,"stop":1745784795294,"duration":310}}]},"204fb7c44c72769850e904d19ad51ab1:9c52a96ff7290b79e517ee08601f8a61":{"statistic":{"failed":1,"broken":0,"skipped":0,"passed":0,"unknown":0,"total":1},"items":[{"uid":"23697d54233d93ba","reportUrl":"https://assurdly.github.io/dfslab-automation-tests/21/11//#testresult/23697d54233d93ba","status":"failed","statusDetails":"Status code is 400","time":{"start":1745784787830,"stop":1745784788574,"duration":744}}]},"b4cced089dd59a73fcd7b4acf0b144b0:be044b1c5d1cf2ad780c7a96173a85d4":{"statistic":{"failed":0,"broken":0,"skipped":0,"passed":1,"unknown":0,"total":1},"items":[{"uid":"91e57961a6435219","reportUrl":"https://assurdly.github.io/dfslab-automation-tests/21/11//#testresult/91e57961a6435219","status":"passed","time":{"start":1745784792394,"stop":1745784792615,"duration":221}}]},"a3c2fc1b9ef50814e3e015448509b0aa:b60067c1736552fbf77b085f35fdd317":{"statistic":{"failed":1,"broken":0,"skipped":0,"passed":0,"unknown":0,"total":1},"items":[{"uid":"92619959fdf6bfbb","reportUrl":"https://assurdly.github.io/dfslab-automation-tests/21/11//#testresult/92619959fdf6bfbb","status":"failed","statusDetails":"Verify that uom is a string and not empty","time":{"start":1745784785853,"stop":1745784786082,"duration":229}}]},"7258beb03cb13821be39e01df728f4f1:b5d7d012f54649d8d7d1d464526002dd":{"statistic":{"failed":0,"broken":0,"skipped":0,"passed":1,"unknown":0,"total":1},"items":[{"uid":"a50af101e2f6fa33","reportUrl":"https://assurdly.github.io/dfslab-automation-tests/21/11//#testresult/a50af101e2f6fa33","status":"passed","time":{"start":1745784792928,"stop":1745784793147,"duration":219}}]},"c09669ff7a02999e817f2bb9b762b6b1:1e01c3be57e55a3cd8765392f08240c1":{"statistic":{"failed":1,"broken":0,"skipped":0,"passed":0,"unknown":0,"total":1},"items":[{"uid":"4e33198f89f91c31","reportUrl":"https://assurdly.github.io/dfslab-automation-tests/21/11//#testresult/4e33198f89f91c31","status":"failed","statusDetails":"Status code is 400","time":{"start":1745784784700,"stop":1745784784823,"duration":123}}]},"dcfb960d6cb2c427c0e4ab040a337d4d:f3c43e0eb717ae7cc3f5ab4846e3d349":{"statistic":{"failed":0,"broken":0,"skipped":0,"passed":1,"unknown":0,"total":1},"items":[{"uid":"76af2eaad01fd7c9","reportUrl":"https://assurdly.github.io/dfslab-automation-tests/21/11//#testresult/76af2eaad01fd7c9","status":"passed","time":{"start":1745784796827,"stop":1745784797081,"duration":254}}]},"824bc776819bba362f9612075180a0e1:74d8190092d3dfa7f03ccd01e5e5d7ba":{"statistic":{"failed":0,"broken":0,"skipped":0,"passed":1,"unknown":0,"total":1},"items":[{"uid":"eeba8ef25f67f5c5","reportUrl":"https://assurdly.github.io/dfslab-automation-tests/21/11//#testresult/eeba8ef25f67f5c5","status":"passed","time":{"start":1745784794762,"stop":1745784794982,"duration":220}}]},"509d883c2e9c58648e323e287d0782da:aecf33aed42b2dda1cc6b752199c97f2":{"statistic":{"failed":0,"broken":0,"skipped":0,"passed":1,"unknown":0,"total":1},"items":[{"uid":"12c3f8ab0b6dcab8","reportUrl":"https://assurdly.github.io/dfslab-automation-tests/21/11//#testresult/12c3f8ab0b6dcab8","status":"passed","time":{"start":1745784785207,"stop":1745784785336,"duration":129}}]},"af2f381285786616240fd6ed12e06b9f:1e01c3be57e55a3cd8765392f08240c1":{"statistic":{"failed":0,"broken":0,"skipped":0,"passed":1,"unknown":0,"total":1},"items":[{"uid":"3e7f7381ef2bc7d2","reportUrl":"https://assurdly.github.io/dfslab-automation-tests/21/11//#testresult/3e7f7381ef2bc7d2","status":"passed","time":{"start":1745784784488,"stop":1745784784697,"duration":209}}]},"16d0677dbb648082f2174544a9dd7ab6:74d8190092d3dfa7f03ccd01e5e5d7ba":{"statistic":{"failed":1,"broken":0,"skipped":0,"passed":0,"unknown":0,"total":1},"items":[{"uid":"2207423c8d5f73cd","reportUrl":"https://assurdly.github.io/dfslab-automation-tests/21/11//#testresult/2207423c8d5f73cd","status":"failed","statusDetails":"Response is an array, Response is an array","time":{"start":1745784795523,"stop":1745784795745,"duration":222}}]},"f1d43cbb3ab042f48d4ba5548c052fe8:e033ae124b2426054c44ca12061af730":{"statistic":{"failed":0,"broken":0,"skipped":0,"passed":1,"unknown":0,"total":1},"items":[{"uid":"213e92da8d9a4a92","reportUrl":"https://assurdly.github.io/dfslab-automation-tests/21/11//#testresult/213e92da8d9a4a92","status":"passed","time":{"start":1745784786557,"stop":1745784787050,"duration":493}}]},"50564a46aca37443acbe2d9146982e1d:74d8190092d3dfa7f03ccd01e5e5d7ba":{"statistic":{"failed":1,"broken":0,"skipped":0,"passed":0,"unknown":0,"total":1},"items":[{"uid":"a0e98e9b8e609b4d","reportUrl":"https://assurdly.github.io/dfslab-automation-tests/21/11//#testresult/a0e98e9b8e609b4d","status":"failed","statusDetails":"Response is an array, Response is an array","time":{"start":1745784795297,"stop":1745784795520,"duration":223}}]},"e8c154ebc6b775bcffaefaca95ded1af:d43c417d1ca10aa8f21e072c6b4112db":{"statistic":{"failed":0,"broken":0,"skipped":0,"passed":1,"unknown":0,"total":1},"items":[{"uid":"69b2ea862e96bc3c","reportUrl":"https://assurdly.github.io/dfslab-automation-tests/21/11//#testresult/69b2ea862e96bc3c","status":"passed","time":{"start":1745784794004,"stop":1745784794224,"duration":220}}]},"62f4cbabe2e5ba40add1c5ab0c5206d7:0b625e035b2b10efb367621919dbf9bd":{"statistic":{"failed":0,"broken":0,"skipped":0,"passed":1,"unknown":0,"total":1},"items":[{"uid":"bb64bee4098f1fde","reportUrl":"https://assurdly.github.io/dfslab-automation-tests/21/11//#testresult/bb64bee4098f1fde","status":"passed","time":{"start":1745784796288,"stop":1745784796595,"duration":307}}]},"5c29d4a6251adb54baaa0a2825687763:b93311c18124bb9fe0a781fd3df1cfd0":{"statistic":{"failed":1,"broken":0,"skipped":0,"passed":0,"unknown":0,"total":1},"items":[{"uid":"172f647e01dc099b","reportUrl":"https://assurdly.github.io/dfslab-automation-tests/21/11//#testresult/172f647e01dc099b","status":"failed","statusDetails":"Status code is 400","time":{"start":1745784790049,"stop":1745784790538,"duration":489}}]},"025e598bd80f3d6072f80b37f393c175:9c52a96ff7290b79e517ee08601f8a61":{"statistic":{"failed":0,"broken":0,"skipped":0,"passed":1,"unknown":0,"total":1},"items":[{"uid":"c236279f2600a6bf","reportUrl":"https://assurdly.github.io/dfslab-automation-tests/21/11//#testresult/c236279f2600a6bf","status":"passed","time":{"start":1745784787544,"stop":1745784787828,"duration":284}}]},"8bfb7682d2eed25815d6bbbae5f02de5:80fb125b05a268f3966bfe2f203d11c0":{"statistic":{"failed":0,"broken":0,"skipped":0,"passed":1,"unknown":0,"total":1},"items":[{"uid":"d6a59a52474d6fa5","reportUrl":"https://assurdly.github.io/dfslab-automation-tests/21/11//#testresult/d6a59a52474d6fa5","status":"passed","time":{"start":1745784785468,"stop":1745784785605,"duration":137}}]},"9045b82a371e842bbfd3b79db0f0c593:b5d7d012f54649d8d7d1d464526002dd":{"statistic":{"failed":0,"broken":0,"skipped":0,"passed":1,"unknown":0,"total":1},"items":[{"uid":"ae36a119267a95d2","reportUrl":"https://assurdly.github.io/dfslab-automation-tests/21/11//#testresult/ae36a119267a95d2","status":"passed","time":{"start":1745784793150,"stop":1745784793459,"duration":309}}]},"420b07828117618d598c23ac207e965f:c81c24e5d01e7831182f57334d4d581b":{"statistic":{"failed":0,"broken":0,"skipped":0,"passed":1,"unknown":0,"total":1},"items":[{"uid":"8c622c2a5ea055d4","reportUrl":"https://assurdly.github.io/dfslab-automation-tests/21/11//#testresult/8c622c2a5ea055d4","status":"passed","time":{"start":1745784790541,"stop":1745784790813,"duration":272}}]},"0ef3fe86ec98063c67764420ec9cf5d7:d43c417d1ca10aa8f21e072c6b4112db":{"statistic":{"failed":0,"broken":0,"skipped":0,"passed":1,"unknown":0,"total":1},"items":[{"uid":"be1e608dda3c8eae","reportUrl":"https://assurdly.github.io/dfslab-automation-tests/21/11//#testresult/be1e608dda3c8eae","status":"passed","time":{"start":1745784794227,"stop":1745784794537,"duration":310}}]},"44eb646d4b03583fb11369a7147ed6a3:3f3daf1ee76fcaff84b0507c03247b77":{"statistic":{"failed":0,"broken":0,"skipped":0,"passed":1,"unknown":0,"total":1},"items":[{"uid":"1c9f7053cc3faa45","reportUrl":"https://assurdly.github.io/dfslab-automation-tests/21/11//#testresult/1c9f7053cc3faa45","status":"passed","time":{"start":1745784793690,"stop":1745784794001,"duration":311}}]},"f0b5351d6e735a4adc1d2f8dfe62b036:be044b1c5d1cf2ad780c7a96173a85d4":{"statistic":{"failed":0,"broken":0,"skipped":0,"passed":1,"unknown":0,"total":1},"items":[{"uid":"9ca8466c5a25e629","reportUrl":"https://assurdly.github.io/dfslab-automation-tests/21/11//#testresult/9ca8466c5a25e629","status":"passed","time":{"start":1745784792618,"stop":1745784792925,"duration":307}}]},"5fa683c22ee68d3972d5163e491a8cac:3f3daf1ee76fcaff84b0507c03247b77":{"statistic":{"failed":0,"broken":0,"skipped":0,"passed":1,"unknown":0,"total":1},"items":[{"uid":"2925fa81d65d352e","reportUrl":"https://assurdly.github.io/dfslab-automation-tests/21/11//#testresult/2925fa81d65d352e","status":"passed","time":{"start":1745784793463,"stop":1745784793688,"duration":225}}]},"3d895fe86f2269d84d211c176a65313f:f3c43e0eb717ae7cc3f5ab4846e3d349":{"statistic":{"failed":0,"broken":0,"skipped":0,"passed":1,"unknown":0,"total":1},"items":[{"uid":"58dba228aefa4e86","reportUrl":"https://assurdly.github.io/dfslab-automation-tests/21/11//#testresult/58dba228aefa4e86","status":"passed","time":{"start":1745784797084,"stop":1745784797390,"duration":306}}]},"b41294a94890f3586abaaa82f05bf104:d49273cb7e7ea6c8e716cc11483620d2":{"statistic":{"failed":1,"broken":0,"skipped":0,"passed":0,"unknown":0,"total":1},"items":[{"uid":"caa0c835f25721b4","reportUrl":"https://assurdly.github.io/dfslab-automation-tests/21/11//#testresult/caa0c835f25721b4","status":"failed","statusDetails":"Status code is 400, Message should indicate failure if data was not fetched","time":{"start":1745784791301,"stop":1745784791808,"duration":507}}]},"3da3ea8388ffe070eae2c41aef1c90d5:74d58197dfb78b6db7a8776c387075ac":{"statistic":{"failed":0,"broken":0,"skipped":0,"passed":1,"unknown":0,"total":1},"items":[{"uid":"a7ff864cca9777e4","reportUrl":"https://assurdly.github.io/dfslab-automation-tests/21/11//#testresult/a7ff864cca9777e4","status":"passed","time":{"start":1745784792062,"stop":1745784792391,"duration":329}}]},"aa89a2d4a1787522c1d84f75834c300a:afab4bde996410008aaf239e3626f3c8":{"statistic":{"failed":0,"broken":0,"skipped":0,"passed":1,"unknown":0,"total":1},"items":[{"uid":"eb930e4ecfe02530","reportUrl":"https://assurdly.github.io/dfslab-automation-tests/21/11//#testresult/eb930e4ecfe02530","status":"passed","time":{"start":1745784788577,"stop":1745784788810,"duration":233}}]},"60a14fe44b214f2aef832c928f7403be:7a85cea52572c67f1f242960341ebcc6":{"statistic":{"failed":0,"broken":0,"skipped":0,"passed":1,"unknown":0,"total":1},"items":[{"uid":"92d4c5d864a70601","reportUrl":"https://assurdly.github.io/dfslab-automation-tests/21/11//#testresult/92d4c5d864a70601","status":"passed","time":{"start":1745784789043,"stop":1745784789296,"duration":253}}]},"bbcb79c3f7e0bd0f90fff7bab3645249:afab4bde996410008aaf239e3626f3c8":{"statistic":{"failed":1,"broken":0,"skipped":0,"passed":0,"unknown":0,"total":1},"items":[{"uid":"8213a434a1463cdf","reportUrl":"https://assurdly.github.io/dfslab-automation-tests/21/11//#testresult/8213a434a1463cdf","status":"failed","statusDetails":"Status code is 400, Response is a non-empty object with number values","time":{"start":1745784788813,"stop":1745784789040,"duration":227}}]},"eee6f9dd3735ef755d0e240a734aab7c:1e01c3be57e55a3cd8765392f08240c1":{"statistic":{"failed":0,"broken":0,"skipped":0,"passed":1,"unknown":0,"total":1},"items":[{"uid":"99bd9b7dd90892b1","reportUrl":"https://assurdly.github.io/dfslab-automation-tests/21/11//#testresult/99bd9b7dd90892b1","status":"passed","time":{"start":1745784784826,"stop":1745784785012,"duration":186}}]},"7d04bd8a182d2b76c0ba1bcfc3e2406c:aecf33aed42b2dda1cc6b752199c97f2":{"statistic":{"failed":1,"broken":0,"skipped":0,"passed":0,"unknown":0,"total":1},"items":[{"uid":"4ea33cc9d6f18974","reportUrl":"https://assurdly.github.io/dfslab-automation-tests/21/11//#testresult/4ea33cc9d6f18974","status":"failed","statusDetails":"Status code is 400","time":{"start":1745784785339,"stop":1745784785465,"duration":126}}]},"97c9b9789465eda36ecb759b44f8bfca:d43c417d1ca10aa8f21e072c6b4112db":{"statistic":{"failed":1,"broken":0,"skipped":0,"passed":0,"unknown":0,"total":1},"items":[{"uid":"4cb2ce5dd4c37af4","reportUrl":"https://assurdly.github.io/dfslab-automation-tests/21/11//#testresult/4cb2ce5dd4c37af4","status":"failed","statusDetails":"Response is an array","time":{"start":1745784794540,"stop":1745784794759,"duration":219}}]},"864fca9367da48867ccd718061e8aa5f:3258e2abfebd29d48e5c03cf74f53633":{"statistic":{"failed":0,"broken":0,"skipped":0,"passed":1,"unknown":0,"total":1},"items":[{"uid":"578853f315de7edf","reportUrl":"https://assurdly.github.io/dfslab-automation-tests/21/11//#testresult/578853f315de7edf","status":"passed","time":{"start":1745784795748,"stop":1745784796060,"duration":312}}]},"2ac5d59c125d269f041db0a61430848f:40213bf39c5c8336a4165563d62cc523":{"statistic":{"failed":0,"broken":0,"skipped":0,"passed":1,"unknown":0,"total":1},"items":[{"uid":"202fdc7b97c88fd7","reportUrl":"https://assurdly.github.io/dfslab-automation-tests/21/11//#testresult/202fdc7b97c88fd7","status":"passed","time":{"start":1745784786085,"stop":1745784786319,"duration":234}}]}}